{"model_fit_params": {"booster": "gbtree", "importance_type": "gain", "learning_rate": 0.05381363494785509, "max_depth": 8, "n_estimators": 457, "n_jobs": -1, "objective": "reg:squarederror", "reg_alpha": 0.6802824674478313, "reg_lambda": 0.13485975857281543, "subsample": 0.6704669549687456, "colsample_bytree": 0.9863955039841362, "colsample_bylevel": 0.8594039653504965, "colsample_bynode": 0.9408677051543407, "gamma": 0.5377846833407581, "min_child_weight": 3, "random_state": 1234, "eval_metric": "mape"}, "model_params": {"objective": "reg:squarederror", "base_score": null, "booster": "gbtree", "callbacks": null, "colsample_bylevel": 0.8594039653504965, "colsample_bynode": 0.9408677051543407, "colsample_bytree": 0.9863955039841362, "device": null, "early_stopping_rounds": null, "enable_categorical": false, "eval_metric": "mape", "feature_types": null, "gamma": 0.5377846833407581, "grow_policy": null, "importance_type": "gain", "interaction_constraints": null, "learning_rate": 0.05381363494785509, "max_bin": null, "max_cat_threshold": null, "max_cat_to_onehot": null, "max_delta_step": null, "max_depth": 8, "max_leaves": null, "min_child_weight": 3, "missing": NaN, "monotone_constraints": null, "multi_strategy": null, "n_estimators": 457, "n_jobs": -1, "num_parallel_tree": null, "random_state": 1234, "reg_alpha": 0.6802824674478313, "reg_lambda": 0.13485975857281543, "sampling_method": null, "scale_pos_weight": null, "subsample": 0.6704669549687456, "tree_method": null, "validate_parameters": null, "verbosity": null}, "metrics": {"r2": 0.908708335834822, "mse": 332114.52493114857, "mae": 244.82747234355412, "mape_test": 0.05256574854736524, "mape_train": 0.021098470655237855}}